Metadata-Version: 2.1
Name: common-robot-interface
Version: 0.5.3
Summary: Common Robot Interface
Home-page: https://github.com/robot-dexterity/common-robot-interface
Author: John Lloyd, Nathan Lepora
Author-email: j.lloyd@bristol.ac.uk, n.lepora@bristol.ac.uk
License: GPLv3
Classifier: Programming Language :: Python :: 3
Classifier: License :: OSI Approved :: GNU General Public License v3 (GPLv3)
License-File: LICENSE
Requires-Dist: numpy
Requires-Dist: transforms3d
